vscode_colab/__init__.py
vscode_colab/logger_config.py
vscode_colab/server.py
vscode_colab/system.py
vscode_colab/templating.py
vscode_colab/utils.py
vscode_colab/assets/gitignore_template.txt
vscode_colab/assets/templates/github_auth_link.html.j2
vscode_colab/assets/templates/vscode_connection_options.html.j2
vscode_colab/environment/__init__.py
vscode_colab/environment/git_handler.py
vscode_colab/environment/project_setup.py
vscode_colab/environment/python_env.py
vscode_colab-0.3.1.dist-info/licenses/LICENSE
vscode_colab-0.3.1.dist-info/METADATA
vscode_colab-0.3.1.dist-info/WHEEL
vscode_colab-0.3.1.dist-info/entry_points.txt
vscode_colab-0.3.1.dist-info/top_level.txt
vscode_colab-0.3.1.dist-info/RECORD
