Metadata-Version: 2.4
Name: vscode-colab
Version: 0.3.1
Summary: A library to set up a VS Code server in Google Colab.
Home-page: https://github.com/EssenceSentry/vscode-colab
Author: EssenceSentry
Author-email: essence.sentry@gmail.com
License: MIT
Classifier: Programming Language :: Python :: 3
Classifier: License :: OSI Approved :: MIT License
Classifier: Intended Audience :: Developers
Requires-Python: >=3.7
License-File: LICENSE
Requires-Dist: requests
Requires-Dist: ipython
Requires-Dist: jinja2
Requires-Dist: loguru
Provides-Extra: testing
Requires-Dist: pytest; extra == "testing"
Requires-Dist: pytest-cov; extra == "testing"
Dynamic: license-file
